[
  {
    "name": "BMW",
    "symbol": "BMW.DE",
    "menu_list": "Automobile",
    "price_purchase": 0.0,
    "price_current": 0.0,
    "price_high": "",
    "price_high_current": 0.0,
    "price_pourcent": 0.0,
    "price_low": "",
    "price_low_current": 0.0,
    "trading_plan_high": "",
    "trading_plan_low": "",
    "message_date": "",
    "message_date_content": "",
    "message_date_to_sent": false,
    "volume_alert": "",
    "volume": 0,
    "vol_tot": 0,
    "vol_max": 0,
    "is_monitoring": false
  },
  {
    "name": "BYD",
    "symbol": "BYDDF",
    "menu_list": "Automobile",
    "price_purchase": 0.0,
    "price_current": 0.0,
    "price_high": "",
    "price_high_current": 0.0,
    "price_pourcent": 0.0,
    "price_low": "",
    "price_low_current": 0.0,
    "trading_plan_high": "",
    "trading_plan_low": "",
    "message_date": "",
    "message_date_content": "",
    "message_date_to_sent": false,
    "volume_alert": "",
    "volume": 0,
    "vol_tot": 0,
    "vol_max": 0,
    "is_monitoring": false
  },
  {
    "name": "HYUNDIA",
    "symbol": "005380.KQ",
    "menu_list": "Automobile",
    "price_purchase": 0.0,
    "price_current": 0.0,
    "price_high": "",
    "price_high_current": 0.0,
    "price_pourcent": 0.0,
    "price_low": "",
    "price_low_current": 0.0,
    "trading_plan_high": "",
    "trading_plan_low": "",
    "message_date": "",
    "message_date_content": "",
    "message_date_to_sent": false,
    "volume_alert": "",
    "volume": 0,
    "vol_tot": 0,
    "vol_max": 0,
    "is_monitoring": false
  },
  {
    "name": "STELLANTIS",
    "symbol": "STLAP.PA",
    "menu_list": "Portefeuille",
    "price_purchase": 18.881,
    "price_current": 0.0,
    "price_high": 15.2,
    "price_high_current": 0.0,
    "price_pourcent": 0.0,
    "price_low": 13.3,
    "price_low_current": 0.0,
    "trading_plan_high": "Résistance",
    "trading_plan_low": "Support",
    "message_date": "",
    "message_date_content": "",
    "message_date_to_sent": false,
    "volume_alert": "",
    "volume": 0,
    "vol_tot": 0,
    "vol_max": 0,
    "is_monitoring": true,
    "volume_max": 20000
  },
  {
    "name": "TOYOTA",
    "symbol": "7203.T",
    "menu_list": "Automobile",
    "price_purchase": 0.0,
    "price_current": 0.0,
    "price_high": "",
    "price_high_current": 0.0,
    "price_pourcent": 0.0,
    "price_low": "",
    "price_low_current": 0.0,
    "trading_plan_high": "",
    "trading_plan_low": "",
    "message_date": "",
    "message_date_content": "",
    "message_date_to_sent": false,
    "volume_alert": "",
    "volume": 0,
    "vol_tot": 0,
    "vol_max": 0,
    "is_monitoring": false
  },
  {
    "name": "VALEO",
    "symbol": "FR.PA",
    "menu_list": "V",
    "price_purchase": 11.965,
    "price_current": 0.0,
    "price_high": 11.6,
    "price_high_current": 0.0,
    "price_pourcent": 0.0,
    "price_low": 11.1,
    "price_low_current": 0.0,
    "trading_plan_high": "Remontée vers le prix de revient ?",
    "trading_plan_low": "Stop LOSS",
    "message_date": "",
    "message_date_content": "",
    "message_date_to_sent": false,
    "volume_alert": "",
    "volume": 0,
    "vol_tot": 0,
    "vol_max": 0,
    "is_monitoring": false,
    "volume_max": 5000
  },
  {
    "name": "VOLKSWAGEN",
    "symbol": "VOW.DE",
    "menu_list": "V",
    "price_purchase": 0.0,
    "price_current": 0.0,
    "price_high": "",
    "price_high_current": 0.0,
    "price_pourcent": 0.0,
    "price_low": "",
    "price_low_current": 0.0,
    "trading_plan_high": "",
    "trading_plan_low": "",
    "message_date": "",
    "message_date_content": "",
    "message_date_to_sent": false,
    "volume_alert": "",
    "volume": 0,
    "vol_tot": 0,
    "vol_max": 0,
    "is_monitoring": false
  }
]